<?xml version="1.0" encoding="UTF-8"?>
<testdata version="0.1">
<trash>
  <keyA>
    fail
  </keyA>
  <keyB>
    fail
  </keyB>
</trash>
<itemA>
  <keyA>A prime</keyA>
  <keyB>B prime</keyB>
</itemA>
<itemB key_x="Xattr first">
  <keyA>not in schema</keyA>
  <key_b keyC="should not open new dictionary">B second</key_b>
  <itemA keyB="should be blind to attribute">
    <keyB>should be blind to this</keyB>
    <keyC>
      <keyD>should still be blind to this</keyD>
    </keyC>
  </itemA>
</itemB>
<itemA>
  <keyC>Entity fun &#39;&gt;</keyC> 
  <keyB>B third</keyB>
</itemA>
<itemD key_one="value_one">
  <key_two>value_two</key_two>
  <key_three subkey_one="subvalue_one">
    <subkey_two>
      <subkey_three>subvalue_three_one</subkey_three>
      <subkey_three>subvalue_three_two</subkey_three>
      <subkey_three>subvalue_three_three</subkey_three>
    </subkey_two>
    <subkey_two>
      <subkey_three>subvalue_three_four</subkey_three>
      <subkey_three>subvalue_three_five</subkey_three>
    </subkey_two>    
  </key_three>
</itemD>
</testdata>
